remit_service/__init__.py
remit_service/app.py
remit_service/base/__init__.py
remit_service/base/base_app.py
remit_service/base/base_cbv.py
remit_service/base/base_router.py
remit_service/base/controller.py
remit_service/base/load_router.py
remit_service/config.py
remit_service/config_manager.py
remit_service/helper/__init__.py
remit_service/helper/config_helper.py
remit_service/helper/ip_helper.py
remit_service/helper/modules_helper.py
remit_service/log/__init__.py
remit_service/nacos/__init__.py
remit_service/nacos/client.py
remit_service/nacos/discovery.py
remit_service/nacos/registry.py
remit_service/static/redoc/bundles/redoc.standalone.js
remit_service/static/redoc/favicon.png
remit_service/static/swagger-ui/favicon-32x32.png
remit_service/static/swagger-ui/swagger-ui-bundle.js
remit_service/static/swagger-ui/swagger-ui.css
remit_service-1.3.6.dist-info/WHEEL
remit_service-1.3.6.dist-info/entry_points.txt
remit_service-1.3.6.dist-info/METADATA
remit_service-1.3.6.dist-info/RECORD
