Metadata-Version: 2.3
Name: remit_service
Version: 1.3.6
Summary: Add your description here
Author: wwt
Author-email: wwt <weiting.wang@easytransfer.cn>
Requires-Dist: fastapi==0.115.0
Requires-Dist: httpx>=0.28.1
Requires-Dist: loguru==0.7.3
Requires-Dist: python-nacos==0.1.1
Requires-Dist: pyyaml==6.0.2
Requires-Dist: uvicorn==0.28.1
Requires-Python: >=3.10
